odoo/addons/mrp_multi_level/README.rst
odoo/addons/mrp_multi_level/__init__.py
odoo/addons/mrp_multi_level/__manifest__.py
odoo/addons/mrp_multi_level/data/mrp_area_data.xml
odoo/addons/mrp_multi_level/data/mrp_multi_level_cron.xml
odoo/addons/mrp_multi_level/demo/initial_on_hand_demo.xml
odoo/addons/mrp_multi_level/demo/mrp_bom_demo.xml
odoo/addons/mrp_multi_level/demo/product_category_demo.xml
odoo/addons/mrp_multi_level/demo/product_mrp_area_demo.xml
odoo/addons/mrp_multi_level/demo/product_product_demo.xml
odoo/addons/mrp_multi_level/demo/product_supplierinfo_demo.xml
odoo/addons/mrp_multi_level/demo/res_partner_demo.xml
odoo/addons/mrp_multi_level/docs/mrp_multi_level_test_run.ods
odoo/addons/mrp_multi_level/i18n/de.po
odoo/addons/mrp_multi_level/i18n/es.po
odoo/addons/mrp_multi_level/i18n/mrp_multi_level.pot
odoo/addons/mrp_multi_level/migrations/11.0.2.0.0/post-migration.py
odoo/addons/mrp_multi_level/models/__init__.py
odoo/addons/mrp_multi_level/models/mrp_area.py
odoo/addons/mrp_multi_level/models/mrp_inventory.py
odoo/addons/mrp_multi_level/models/mrp_move.py
odoo/addons/mrp_multi_level/models/mrp_planned_order.py
odoo/addons/mrp_multi_level/models/product_mrp_area.py
odoo/addons/mrp_multi_level/models/product_product.py
odoo/addons/mrp_multi_level/models/product_template.py
odoo/addons/mrp_multi_level/models/stock_location.py
odoo/addons/mrp_multi_level/readme/CONFIGURE.rst
odoo/addons/mrp_multi_level/readme/CONTRIBUTORS.rst
odoo/addons/mrp_multi_level/readme/DESCRIPTION.rst
odoo/addons/mrp_multi_level/readme/HISTORY.rst
odoo/addons/mrp_multi_level/readme/USAGE.rst
odoo/addons/mrp_multi_level/security/ir.model.access.csv
odoo/addons/mrp_multi_level/security/mrp_multi_level_security.xml
odoo/addons/mrp_multi_level/static/description/icon.png
odoo/addons/mrp_multi_level/static/description/index.html
odoo/addons/mrp_multi_level/static/src/img/icon.png
odoo/addons/mrp_multi_level/tests/__init__.py
odoo/addons/mrp_multi_level/tests/test_mrp_multi_level.py
odoo11_addon_mrp_multi_level-11.0.3.3.0.dist-info/METADATA
odoo11_addon_mrp_multi_level-11.0.3.3.0.dist-info/WHEEL
odoo11_addon_mrp_multi_level-11.0.3.3.0.dist-info/top_level.txt
odoo11_addon_mrp_multi_level-11.0.3.3.0.dist-info/RECORD
